mvmt/__init__.py
mvmt/algebra.py
mvmt/parser.out
mvmt/parsetab.py
mvmt/syntax.py
mvmt/tableau.py
mvmt/utils.py
mvmt-0.0.9.dist-info/METADATA
mvmt-0.0.9.dist-info/WHEEL
mvmt-0.0.9.dist-info/licenses/LICENSE
mvmt-0.0.9.dist-info/RECORD
