Metadata-Version: 2.1
Name: mvmt
Version: 0.0.9
Summary: A package for checking the validity of many-valued modal formulas
Project-URL: repository, https://github.com/WeAreDevo/Many-Valued-Modal-Tableau
Project-URL: Homepage, https://github.com/WeAreDevo/Many-Valued-Modal-Tableau
Project-URL: Bug Tracker, https://github.com/WeAreDevo/Many-Valued-Modal-Tableau/issues
Author-email: Guy Axelrod <g.axelrod1@gmail.com>
License-Expression: MIT
License-File: LICENSE
Keywords: logic,modal logic,tableau
Classifier: License :: OSI Approved :: MIT License
Classifier: Operating System :: OS Independent
Classifier: Programming Language :: Python :: 3
Requires-Python: >=3.8
Requires-Dist: matplotlib
Requires-Dist: networkx
Requires-Dist: ply
Requires-Dist: prettyprinttree
